[
    {
        "Name": "M12词组",
        "Words": [
            {
                "English": "traditional western music",
                "PhoneticSymbols": "",
                "Chinese": "西方传统音乐"
            },
            {
                "English": "the capital of Austria",
                "PhoneticSymbols": "",
                "Chinese": "奥地利首都"
            },
            {
                "English": "go through",
                "PhoneticSymbols": "",
                "Chinese": "流经"
            },
            {
                "English": "listen to the fantastic voice",
                "PhoneticSymbols": "",
                "Chinese": "听着绝妙的嗓音"
            },
            {
                "English": "a fan of rock music",
                "PhoneticSymbols": "",
                "Chinese": "摇滚乐迷"
            },
            {
                "English": "give us a break",
                "PhoneticSymbols": "",
                "Chinese": "饶了我们吧(得了吧,让我们清静会吧)"
            },
            {
                "English": "much too fast/heavy",
                "PhoneticSymbols": "",
                "Chinese": "太快/沉"
            },
            {
                "English": "too much work/water",
                "PhoneticSymbols": "",
                "Chinese": "太多工作/水"
            },
            {
                "English": "know little/much about",
                "PhoneticSymbols": "",
                "Chinese": "不太了解/非常了解"
            },
            {
                "English": "the center of European classical music",
                "PhoneticSymbols": "",
                "Chinese": "欧洲古典音乐的中心"
            },
            {
                "English": "take sb. around",
                "PhoneticSymbols": "",
                "Chinese": "带…周游"
            },
            {
                "English": "give concerts",
                "PhoneticSymbols": "",
                "Chinese": "开音乐会"
            },
            {
                "English": "hundreds of wonderful pieces of music",
                "PhoneticSymbols": "",
                "Chinese": "几百部动听的音乐作品"
            },
            {
                "English": "at an early age",
                "PhoneticSymbols": "",
                "Chinese": "在…早年间"
            },
            {
                "English": "come out",
                "PhoneticSymbols": "",
                "Chinese": "发表,出版"
            },
            {
                "English": "lose one's hearing",
                "PhoneticSymbols": "",
                "Chinese": "丧失听力"
            },
            {
                "English": "in the last ten years of Beethoven's life",
                "PhoneticSymbols": "",
                "Chinese": "在贝多芬生命的最后十年里"
            },
            {
                "English": "take place",
                "PhoneticSymbols": "",
                "Chinese": "发生"
            }
        ]
    },
    {
        "Name": "M12句子",
        "Words": [
            {
                "English": "The Blue Danube is Western music, isn't it Yes, it is.",
                "PhoneticSymbols": "",
                "Chinese": "《蓝色多瑙河》是西方音乐,是吧?是的"
            },
            {
                "English": "Is this piece of music by Strauss or Mozart? It's by Strauss.",
                "PhoneticSymbols": "",
                "Chinese": "这首曲子时施特劳斯的作品还是莫扎特的作品。是施特劳斯的作品"
            },
            {
                "English": "What a beautiful city (it is) How beautiful the city is!",
                "PhoneticSymbols": "",
                "Chinese": "一座很美丽的城市"
            },
            {
                "English": "Do you like rock music or pop music? I like both.",
                "PhoneticSymbols": "",
                "Chinese": "你喜欢摇滚乐还是流行音乐?我都喜欢。"
            },
            {
                "English": "You listen to modern music, don’t you? No, I don’t.",
                "PhoneticSymbols": "",
                "Chinese": "你听现代音乐,对吧?不,我不听。"
            },
            {
                "English": "What noisy drums they are playing!",
                "PhoneticSymbols": "",
                "Chinese": "他们正在击打的鼓声很大"
            },
            {
                "English": "What music do you like? I like pop, because it's lively and good to dance to.",
                "PhoneticSymbols": "",
                "Chinese": "你喜欢什么音乐?我喜欢流行音乐,因为它很轻快,很适合跳舞。"
            },
            {
                "English": "The father, J S the elder, wrote and played music for traditional dances, called the waltz.",
                "PhoneticSymbols": "",
                "Chinese": "父亲老约翰·施特劳斯创作并演奏一种古典舞曲,叫华尔兹。"
            },
            {
                "English": "His dance music made him famous all over Europe.",
                "PhoneticSymbols": "",
                "Chinese": "他的舞曲让他闻名欧洲"
            },
            {
                "English": "M was another very important composer.",
                "PhoneticSymbols": "",
                "Chinese": "莫扎特是另一位非常重要的作曲家。"
            },
            {
                "English": "Before he was six, he played not only the piano but also the violin.",
                "PhoneticSymbols": "",
                "Chinese": "他不到六岁,就不仅会弹钢琴,还会拉小提琴。"
            },
            {
                "English": "He became very poor and died in 1791 when he was only 35.",
                "PhoneticSymbols": "",
                "Chinese": "他变得很穷困,于1791年去世,年仅35岁。"
            },
            {
                "English": "I don’t believe the sound is very different.",
                "PhoneticSymbols": "",
                "Chinese": "我简直无法相信这个声音太不一样了。"
            },
            {
                "English": "In the eighteenth century, a lot of musicians came to study and work in Vienna.",
                "PhoneticSymbols": "",
                "Chinese": "在十八世纪,许多音乐家到维也纳学习和工作。"
            },
            {
                "English": "Like J S, father and son, he was a great European musician, and many people still think his music is perfect.",
                "PhoneticSymbols": "",
                "Chinese": "像施特劳斯父子一样,他是一位伟大的欧洲音乐家,现在许多人仍然认为他的音乐是完美的。"
            },
            {
                "English": "Vienna is a beautiful old city on the River Danube in the center of Europe.",
                "PhoneticSymbols": "",
                "Chinese": "维也纳是位于欧洲中部多瑙河畔的一座古老而美丽的城市。"
            },
            {
                "English": "In the S family, there were two composers called Johann S, the father and the son.",
                "PhoneticSymbols": "",
                "Chinese": "在施特劳斯家族,有两位名为约翰·施特劳斯的作家:父亲和儿子。"
            }
        ]
    }
]